sidspackage/__init__.py
sidspackage/colorprint.py
sidspackage/paginator.py
sidspackage-0.0.4.dist-info/LICENCE.txt
sidspackage-0.0.4.dist-info/METADATA
sidspackage-0.0.4.dist-info/WHEEL
sidspackage-0.0.4.dist-info/top_level.txt
sidspackage-0.0.4.dist-info/RECORD
