Metadata-Version: 2.1
Name: sidspackage
Version: 0.0.4
Summary: This is my first PyPi package, so its mainly a test
Home-page: https://github.com/FusionSid/sids-package
Author: Siddhesh Zantye
Author-email: siddheshadsv@icloud.com
License: UNKNOWN
Platform: UNKNOWN
License-File: LICENCE.txt
